{
    "document_id": "RA_1333",
    "title": "AN ACT CHANGING THE NAMES OF CERTAIN BARRIOS IN THE MUNICIPALITY OF NAVAL PROVINCE OF LEYTE.",
    "date_approved": "June 16, 1955",
    "source": "https://elibrary.judiciary.gov.ph/thebookshelf/showdocs/2/22068",
    "chunks": [
        {
            "chunk_index": 1,
            "text": "H. No. 3564 / 51 OG No. 8, 3882 (August, 1955)\n\n[ REPUBLIC ACT NO. 1333, June 16, 1955 ]\n\nAN ACT CHANGING THE NAMES OF CERTAIN BARRIOS IN THE MUNICIPALITY OF NAVAL PROVINCE OF LEYTE.\n\nBe it enacted by the Senate and House of Representatives of the Philippines in Congress assembled:\n\nSECTION 1. The names of the following: barrios in the Municipality of Naval, Province of Leyte, are changed as follows:\n\nBarrio Catmon to barrio Santo Rosario; barrio Agpangi to barrio La Purisima Concepcion; barrio Lico to barrio San Vicente; barrio Talostusan to barrio Santa Fe; barrio Locso-on to barrio San Isidro; and barrio Villa Caneja to barrio Sulphur Valley.\n\nSEC. 2. This Act shall take effect upon its approval.\n\nApproved, June 16, 1955.",
            "metadata": {
                "law_id": "RA_1333",
                "date": "June 16, 1955"
            }
        }
    ]
}