{
    "document_id": "RA_10671",
    "title": "AN ACT CHANGING THE NAME OF GUBAT DISTRICT HOSPITAL TO SALVADOR R. ENCINAS DISTRICT HOSPITAL IN GUBAT, SORSOGON",
    "date_approved": "August 19, 2015",
    "source": "https://elibrary.judiciary.gov.ph/thebookshelf/showdocs/2/63749",
    "chunks": [
        {
            "chunk_index": 1,
            "text": "H. No. 1248; Manila Bulletin, August 25, 2015; 111 OG No. 40, 5825 (October 5, 2015)\n\n[ REPUBLIC ACT NO. 10671, August 19, 2015 ]\n\nAN ACT CHANGING THE NAME OF GUBAT DISTRICT HOSPITAL TO SALVADOR R. ENCINAS DISTRICT HOSPITAL IN GUBAT, SORSOGON\n\nBe it enacted by the Senate and House of Representatives of the Philippines in Congress assembled:\n\nSECTION 1.\n\nChange of Hospital Name. –\n\nThe name of Gubat District Hospital in the Municipality of Gubat, Province of Sorsogon is hereby changed to Salvador R. Encinas District Hospital.\n\nSEC. 2.\n\nEffectivity.\n\n– This Act shall take effect fifteen (15) days after its publication in any newspaper of general circulation.\n\n(SGD.) FRANKLIN M. DRILON\n\nPresident of the Senate\n\n(SGD.) FELICIANO BELMONTE JR.\n\nSpeaker of the House\n\nof Representatives\n\nThis Act which originated in the House of Representatives was passed by the House of Representatives and the Senate on February 10, 2014 and May 25, 2015, respectively.\n\n(SGD.) OSCAR G. YABES\n\nSecretary of the Senate\n\n(SGD.) MARILYN B. BARUA-YAP\n\nSecretary General\n\nHouse of Representatives\n\nApproved: AUG 19 2015\n\n(SGD.) BENIGNO S. AQUINO III\n\nPresident of the Philippines",
            "metadata": {
                "law_id": "RA_10671",
                "date": "August 19, 2015"
            }
        }
    ]
}