{
    "document_id": "RA_10147",
    "title": "AN ACT APPROPRIATING FUNDS FOR THE OPERATION OF THE GOVERNMENT OF THE REPUBLIC OF THE PHILIPPINES FROM JANUARY ONE TO DECEMBER THIRTY-ONE, TWO THOUSAND AND ELEVEN, AND FOR OTHER PURPOSES",
    "date_approved": "January 01, 2011",
    "source": "https://elibrary.judiciary.gov.ph/thebookshelf/showdocs/2/74524",
    "chunks": [
        {
            "chunk_index": 1,
            "text": "[ REPUBLIC ACT NO. 10147, January 01, 2011 ]\n\nAN ACT APPROPRIATING FUNDS FOR THE OPERATION OF THE GOVERNMENT OF THE REPUBLIC OF THE PHILIPPINES FROM JANUARY ONE TO DECEMBER THIRTY-ONE, TWO THOUSAND AND ELEVEN, AND FOR OTHER PURPOSES\n\nSee GENERAL APPROPRIATIONS ACT (January 1 - December 31, 2011)",
            "metadata": {
                "law_id": "RA_10147",
                "date": "January 01, 2011"
            }
        }
    ]
}