{
    "document_id": "RA_1473",
    "title": "AN ACT TO AMEND SECTION TWO, ap. QUEZON, ITEM THIRTY-THREE, PAGE FIVE HUNDRED SEVENTY-EIGHT, OF REPUBLIC ACT NUMBERED TWELVE HUNDRED.",
    "date_approved": "June 14, 1956",
    "source": "https://elibrary.judiciary.gov.ph/thebookshelf/showdocs/2/11937",
    "chunks": [
        {
            "chunk_index": 1,
            "text": "H. No. 4728 / 52 OG No. 7, 3536 (July, 1956)\n\n[ REPUBLIC ACT NO. 1473, June 14, 1956 ]\n\nAN ACT TO AMEND SECTION TWO, ap. QUEZON, ITEM THIRTY-THREE, PAGE FIVE HUNDRED SEVENTY-EIGHT, OF REPUBLIC ACT NUMBERED TWELVE HUNDRED.\n\nBe it enacted by the Senate and House of Representatives of the Philippines in Congress assembled:\n\nSECTION 1. Section two, ap. Quezon, Item. thirty-three, page five hundred seventy-eight, of Republic Act Numbered Twelve hundred is amended to read as follows:\n\n\"33. Construction of additional building, Bignay Barrio School, Sariaya……….P6,000.00\"\n\nSEC. 2. This Act shall take effect upon its approval.",
            "metadata": {
                "law_id": "RA_1473",
                "date": "June 14, 1956"
            }
        }
    ]
}