{
    "document_id": "RA_2216",
    "title": "AN ACT CHANGING THE NAME OF THE BARRIO OF TAMBON IN THE MUNICIPALITY OF ALICIA, PROVINCE OF ZAMBOANGA DEL SUR, TO BARRIO TANDIONG MUSLIM.",
    "date_approved": "May 16, 1959",
    "source": "https://elibrary.judiciary.gov.ph/thebookshelf/showdocs/2/11679",
    "chunks": [
        {
            "chunk_index": 1,
            "text": "H. No. 780 / 55 OG No. 27, 4986 (July 6, 1959)\n\n[ REPUBLIC ACT NO. 2216, May 16, 1959 ]\n\nAN ACT CHANGING THE NAME OF THE BARRIO OF TAMBON IN THE MUNICIPALITY OF ALICIA, PROVINCE OF ZAMBOANGA DEL SUR, TO BARRIO TANDIONG MUSLIM.\n\nBe it enacted by the Senate and House of Representatives of the Philippines in Congress assembled:\n\nSECTION 1. The name of the barrio of Tambon in the Municipality of Alicia, Province of Zamboanga del Sur, is changed to barrio Tandiong Muslim.\n\nSEC. 2. This Act shall take effect upon its approval.\n\nEnacted without executive approval, May 16, 1959.",
            "metadata": {
                "law_id": "RA_2216",
                "date": "May 16, 1959"
            }
        }
    ]
}