{
    "document_id": "RA_2638",
    "title": "AN ACT TO AMEND SECTION ONE OF REPUBLIC ACT NUMBERED SIXTEEN HUNDRED TWENTY-THREE, REGARDING THE EXTENSION OF THE SOUTHERN LINE OF THE MANILA RAILROAD COMPANY TO MATNOG, SORSOGON.",
    "date_approved": "June 18, 1960",
    "source": "https://elibrary.judiciary.gov.ph/thebookshelf/showdocs/2/24542",
    "chunks": [
        {
            "chunk_index": 1,
            "text": "H. No. 1727 / 56 OG No. 38, 5851 (September 19, 1960)\n\n[ REPUBLIC ACT NO. 2638, June 18, 1960 ]\n\nAN ACT TO AMEND SECTION ONE OF REPUBLIC ACT NUMBERED SIXTEEN HUNDRED TWENTY-THREE, REGARDING THE EXTENSION OF THE SOUTHERN LINE OF THE MANILA RAILROAD COMPANY TO MATNOG, SORSOGON.\n\nBe it enacted by the Senate and House of Representatives of the Philippines in congress assembled:\n\nSECTION 1. Section one of Republic Act Numbered Sixteen hundred twenty-three is amended to read as follows:\n\n\"SECTION 1. the amount of fifteen million pesos is appropriated, out of the proceeds of the sales of bonds authorized under republic act numbered one thousand, upon recommendation of the national economic council, and/or the proceeds of the reparations from Japan, for the extension of the southern line of the Manila Railroad Company from the municipality of Daraga, Province of Albay, to the Municipality of Matnog, Province of Sorsogon.\"\n\nSEC. 2. This Act shall take effect upon its approval.\n\nApproved, June 18, 1960.",
            "metadata": {
                "law_id": "RA_2638",
                "date": "June 18, 1960"
            }
        }
    ]
}