{
    "document_id": "RA_2531",
    "title": "AN ACT CHANGING THE NAME OF BARRIO BOHÓ IN THE MUNICIPALITY OF CASIGURAN, PROVINCE OF SORSOGON, TO SAN ANTONIO.",
    "date_approved": "June 21, 1959",
    "source": "https://elibrary.judiciary.gov.ph/thebookshelf/showdocs/2/14449",
    "chunks": [
        {
            "chunk_index": 1,
            "text": "H. No. 1356 / 55 OG No. 38, 8099 (September 21, 1959)\n\n[ REPUBLIC ACT NO. 2531, June 21, 1959 ]\n\nAN ACT CHANGING THE NAME OF BARRIO BOHÓ IN THE MUNICIPALITY OF CASIGURAN, PROVINCE OF SORSOGON, TO SAN ANTONIO.\n\nBe it enacted by the Senate and House of Representatives of the Philippines in Congress assembled:\n\nSECTION 1. The name of Barrio Bohó in the Municipality of Casiguran, Province of Sorsogon, is hereby changed to San Antonio.\n\nSEC. 2. This Act shall take effect upon its approval.\n\nEnacted without executive approval, June 21, 1959.",
            "metadata": {
                "law_id": "RA_2531",
                "date": "June 21, 1959"
            }
        }
    ]
}