{
    "document_id": "RA_2455",
    "title": "AN ACT TO AMEND ITEM (G), GROUP II, PAGE 29, SUBPARAGRAPH (10), FOR THE PROVINCE OF BULACAN, PARAGRAPH \"f,\" SECTION TWO OF REPUBLIC ACT NUMBERED SIXTEEN HUNDRED THIRTEEN.",
    "date_approved": "June 21, 1959",
    "source": "https://elibrary.judiciary.gov.ph/thebookshelf/showdocs/2/13973",
    "chunks": [
        {
            "chunk_index": 1,
            "text": "H. No. 2976 / 55 OG No. 35, 7310 (August 31, 1959)\n\n[ REPUBLIC ACT NO. 2455, June 21, 1959 ]\n\nAN ACT TO AMEND ITEM (\n\nG\n\n), GROUP II, PAGE 29, SUBPARAGRAPH (10), FOR THE PROVINCE OF BULACAN, PARAGRAPH \"f,\" SECTION TWO OF REPUBLIC ACT NUMBERED SIXTEEN HUNDRED THIRTEEN.\n\nBe it enacted by the Senate and House of Representatives of the Philippines in Congress assembled:\n\nSECTION 1. Item (\n\ng\n\n), group II, page 29, subparagraph (10), for the Province of Bulacan, paragraph \"f,\" section two of Republic Act Numbered Sixteen hundred thirteen is amended to read as follows:\n\n\"(\n\ng\n\n)\n\nSta. Maria Public Market Acquisition of site and construction\n\nP15.000.00\"\n\nSEC. 2. This Act shall take effect upon its approval.\n\nEnacted without executive approval, June 21, 1959.",
            "metadata": {
                "law_id": "RA_2455",
                "date": "June 21, 1959"
            }
        }
    ]
}