{
    "document_id": "RA_3526",
    "title": "AN ACT AUTHORIZING THE REVERSION OF UNLIQUIDATED BALANCES OF ACCOUNTS PAYABLE OUTSTANDING FOR TWO YEARS OR MORE.",
    "date_approved": "June 20, 1963",
    "source": "https://elibrary.judiciary.gov.ph/thebookshelf/showdocs/2/25712",
    "chunks": [
        {
            "chunk_index": 1,
            "text": "S. No. 476 / 59 OG No. 59, 5236 (August 19, 1963)\n\n[ REPUBLIC ACT NO. 3526, June 20, 1963 ]\n\nAN ACT AUTHORIZING THE REVERSION OF UNLIQUIDATED BALANCES OF ACCOUNTS PAYABLE OUTSTANDING FOR TWO YEARS OR MORE.\n\nBe it enacted by the Senate and House of Representatives of the Philippines in Congress assembled:\n\nSECTION 1. Any provision of law to the contrary notwithstanding, the Auditor General, upon notice to the Head of the Office or agency concerned, may revert to the unappropriated surplus of the General fund of the National Government, any unliquidated balances of accounts payable in the books of the National Government which have been outstanding for two years or more and against which no actual claims, administrative or judicial, have been filed or which are not covered by perfected contracts on record:\n\nProvided\n\n, That the provision of this section shall not apply to unliquidated balances of accounts payable in trust funds as long as the purposes for which such funds have been created have not been accomplished.",
            "metadata": {
                "law_id": "RA_3526",
                "date": "June 20, 1963"
            }
        },
        {
            "chunk_index": 2,
            "text": "SEC. 2. There is hereby appropriated out of any funds in the National Treasury not otherwise appropriated such sums as may be necessary to settle legitimate obligations which may not have been paid by reason of the reversion provided in Section 1 hereof:\n\nProvided\n\n, That this shall not be construed as an authority to revive claims already barred by prescription or disallowed by a final administrative or judicial determination.\n\nSEC. 3. This Act shall take effect upon its approval.\n\nApproved, June 20, 1963.",
            "metadata": {
                "law_id": "RA_3526",
                "date": "June 20, 1963"
            }
        }
    ]
}