{
    "document_id": "RA_3078",
    "title": "AN ACT PROVIDING FOR TWO ASSISTANT PROVINCIAL FISCALS FOR THE PROVINCE OF SOUTHERN LEYTE, BY FURTHER AMENDING SECTION SIXTEEN HUNDRED SEVENTY-FOUR OF THE ADMINISTRATIVE CODE.",
    "date_approved": "June 17, 1961",
    "source": "https://elibrary.judiciary.gov.ph/thebookshelf/showdocs/2/20834",
    "chunks": [
        {
            "chunk_index": 1,
            "text": "H. No. 5039 / 57 OG No. 49, 8818 (December 4, 1961)\n\n[ REPUBLIC ACT NO. 3078, June 17, 1961 ]\n\nAN ACT PROVIDING FOR TWO ASSISTANT PROVINCIAL FISCALS FOR THE PROVINCE OF SOUTHERN LEYTE, BY FURTHER AMENDING SECTION SIXTEEN HUNDRED SEVENTY-FOUR OF THE ADMINISTRATIVE CODE.\n\nBe it enacted by the Senate and House of Representatives of the Philippines in Congress assembled:\n\nSECTION 1. Section sixteen hundred seventy-four of the Administrative Code, as amended, relative to assistant provincial fiscals, is further amended so that the Province of Southern Leyte shall have two assistant provincial fiscals.\n\nSEC. 2. This Act shall take effect upon its approval.\n\nApproved, June 17, 1961.",
            "metadata": {
                "law_id": "RA_3078",
                "date": "June 17, 1961"
            }
        }
    ]
}