{
    "document_id": "RA_3306",
    "title": "AN ACT TO AMEND A CERTAIN ITEM IN REPUBLIC ACT NUMBERED TWENTY-SEVEN HUNDRED AND ONE.",
    "date_approved": "June 18, 1961",
    "source": "https://elibrary.judiciary.gov.ph/thebookshelf/showdocs/2/19793",
    "chunks": [
        {
            "chunk_index": 1,
            "text": "H. No. 5417 / 58 OG No. 16, 3325 (April 16, 1962)\n\n[ REPUBLIC ACT NO. 3306, June 18, 1961 ]\n\nAN ACT TO AMEND A CERTAIN ITEM IN REPUBLIC ACT NUMBERED TWENTY-SEVEN HUNDRED AND ONE.\n\nBe it enacted by the Senate and House of Representatives of the Philippines in Congress assembled:\n\nSECTION 1. Item (h), sub-paragraph Cebu III, page 340, Section 2-c, Republic Act Numbered Twenty-seven hundred and one is hereby amended to read as follows:\n\n\"(h) Napo Elementary School Building,Carcar Construction of 2 rooms, \"Noel\" Type\n\nP8,000.00\"\n\nSEC. 2. This Act shall take effect upon its approval.\n\nEnacted, without Executive approval, June 18, 1961.",
            "metadata": {
                "law_id": "RA_3306",
                "date": "June 18, 1961"
            }
        }
    ]
}