{
    "document_id": "RA_4707",
    "title": "AN ACT AMENDING SECTION THREE (A) OF REPUBLIC ACT NUMBERED SIX HUNDRED TWO, AS AMENDED BY REPUBLIC ACT NUMBERED FOUR THOUSAND ONE HUNDRED EIGHTY, SO AS TO INCLUDE EMPLOYEES OF MINING ENTERPRISES WITHIN THE PURVIEW OF SAID ACT.",
    "date_approved": "June 18, 1966",
    "source": "https://elibrary.judiciary.gov.ph/thebookshelf/showdocs/2/3515",
    "chunks": [
        {
            "chunk_index": 1,
            "text": "H. No. 571 / 64 OG No. 49, 12583 (December 2, 1968)\n\n[ REPUBLIC ACT NO. 4707, June 18, 1966 ]\n\nAN ACT AMENDING SECTION THREE (A) OF REPUBLIC ACT NUMBERED SIX HUNDRED TWO, AS AMENDED BY REPUBLIC ACT NUMBERED FOUR THOUSAND ONE HUNDRED EIGHTY, SO AS TO INCLUDE EMPLOYEES OF MINING ENTERPRISES WITHIN THE PURVIEW OF SAID ACT.\n\nBe it enacted by the Senate and House of Representatives of the Philippines in Congress assembled:\n\nSECTION 1. Section three (\n\na\n\n) of Republic Act Numbered Six hundred two, as amended by Republic Act Numbered Four thousand one hundred eighty, is hereby further amended to read as fallows:\n\n\"SEC. 3.\n\nMinimum Wage\n\n.—(\n\na\n\n) Every employer shall pay to each of his employees who is employed by an enterprise other than in agriculture minimum wages of not less than six pesos a day:\n\nProvided,\n\nThat this Act shall not apply to any retail or service enterprise that regularly employs not more than five employees;\"\n\nSEC. 2. This Act shall take effect upon its approval.\n\nApproved, June 18, 1966.",
            "metadata": {
                "law_id": "RA_4707",
                "date": "June 18, 1966"
            }
        }
    ]
}