{
    "document_id": "RA_4306",
    "title": "AN ACT CREATING THE BARRIO OF HIPANTAG IN THE MUNICIPALITY OF SOGOD, PROVINCE OF SOUTHERN LEYTE.",
    "date_approved": "June 19, 1965",
    "source": "https://elibrary.judiciary.gov.ph/thebookshelf/showdocs/2/6733",
    "chunks": [
        {
            "chunk_index": 1,
            "text": "H. No. 9192 / 62 OG No. 25, 4383 (June 20, 1966)\n\n[ REPUBLIC ACT NO. 4306, June 19, 1965 ]\n\nAN ACT CREATING THE BARRIO OF HIPANTAG IN THE MUNICIPALITY OF SOGOD, PROVINCE OF SOUTHERN LEYTE.\n\nBe it enacted by the Senate and House of Representatives of the Philippines in Congress assembled:\n\nSECTION 1. The sitio of Hipantag in the barrio of Benit, Municipality of Sogod, Province of Southern Leyte, is separated from said barrio and constituted into a distinct and independent barrio of said municipality, to be known as the barrio of Hipantag.\n\nSEC. 2. This Act shall take effect upon its approval.\n\nApproved, June 19, 1965.",
            "metadata": {
                "law_id": "RA_4306",
                "date": "June 19, 1965"
            }
        }
    ]
}