{
    "document_id": "RA_4328",
    "title": "AN ACT INCREASING THE NUMBER OF ASSISTANT PROVINCIAL FISCALS FOR THE PROVINCE OF ORIENTAL MINDORO, AMENDING FOR THE PURPOSE SECTION SIXTEEN HUNDRED SEVENTY-FOUR OF THE ADMINISTRATIVE CODE, AS AMENDED.",
    "date_approved": "June 19, 1965",
    "source": "https://elibrary.judiciary.gov.ph/thebookshelf/showdocs/2/1413",
    "chunks": [
        {
            "chunk_index": 1,
            "text": "H. No. 11671 / 62 OG No. 27, 4748 (July 4, 1966)\n\n[ REPUBLIC ACT NO. 4328, June 19, 1965 ]\n\nAN ACT INCREASING THE NUMBER OF ASSISTANT PROVINCIAL FISCALS FOR THE PROVINCE OF ORIENTAL MINDORO, AMENDING FOR THE PURPOSE SECTION SIXTEEN HUNDRED SEVENTY-FOUR OF THE ADMINISTRATIVE CODE, AS AMENDED.\n\nBe it enacted by the Senate and House of Representatives of the Philippines in Congress assembled:\n\nSECTION 1. The provision of Section sixteen hundred seventy-four of the Administrative Code, as amended, relative to the number of assistant provincial fiscals in the Province of Oriental Mindoro, is further amended to read as follows:\n\n\"Oriental Mindoro, five;\"\n\nSEC. 2. This Act shall take effect upon its approval;\n\nApproved, June 19, 1965.",
            "metadata": {
                "law_id": "RA_4328",
                "date": "June 19, 1965"
            }
        }
    ]
}