{
    "document_id": "RA_4218",
    "title": "AN ACT CREATING CERTAIN BARRIOS IN THE MUNICIPALITY OF SAN POLICARPO, PROVINCE OF SAMAR.",
    "date_approved": "June 19, 1965",
    "source": "https://elibrary.judiciary.gov.ph/thebookshelf/showdocs/2/6617",
    "chunks": [
        {
            "chunk_index": 1,
            "text": "H. No. 1675 / 62 OG No. 21, 3546 (May 23, 1966)\n\n[ REPUBLIC ACT NO. 4218, June 19, 1965 ]\n\nAN ACT CREATING CERTAIN BARRIOS IN THE MUNICIPALITY OF SAN POLICARPO, PROVINCE OF SAMAR.\n\nBe it enacted by the Senate and House of Representatives of the Philippines in Congress assembled:\n\nSECTION 1. The sitios of Sta. Cruz, Tan-awan, Bangon, Guin-osokan, Barras, Lipata and Libas in the Municipality of San Policarpo, Province of Samar, are converted into barrios of said municipality, to be known as the Barrios of Sta. Cruz, Tanawan, Bangon, Guin-osokan, Barras, Lipata and Libas, respectively.\n\nSEC. 2. This Act shall take effect upon its approval.\n\nApproved, June 19, 1965.",
            "metadata": {
                "law_id": "RA_4218",
                "date": "June 19, 1965"
            }
        }
    ]
}