{
    "document_id": "RA_4778",
    "title": "AN ACT CREATING BARRIO BALANTOY, MUNICIPALITY OF BALBALAN, MOUNTAIN PROVINCE",
    "date_approved": "June 18, 1966",
    "source": "https://elibrary.judiciary.gov.ph/thebookshelf/showdocs/2/25166",
    "chunks": [
        {
            "chunk_index": 1,
            "text": "H. No. 853 / 65 OG No. 3, 521 (January 20, 1969)\n\n[ REPUBLIC ACT NO. 4778, June 18, 1966 ]\n\nAN ACT CREATING BARRIO BALANTOY, MUNICIPALITY OF BALBALAN, MOUNTAIN PROVINCE\n\nBe it enacted by the Senate and House of Representatives of the Philippines in Congress assembled:\n\nSECTION 1. Sitios Balantoy, Ligayan, Kilayon, Bolo and Nawoy, Municipality of Balbalan, Mountain Province, are constituted into a barrio, to be known as Barrio Balantoy of said municipality.\n\nSEC. 2. This Act shall take effect upon its approval.\n\nApproved, June 18, 1966.",
            "metadata": {
                "law_id": "RA_4778",
                "date": "June 18, 1966"
            }
        }
    ]
}