{
    "document_id": "RA_4424",
    "title": "AN ACT TO ESTABLISH A NATIONAL SCHOOL OF ARTS AND TRADES IN THE MUNICIPALITY OF CERVANTES, PROVINCE OF ILOCOS SUR, TO BE KNOWN AS CERVANTES NATIONAL SCHOOL OF ARTS AND TRADES, AND TO AUTHORIZE THE APPROPRIATION OF NECESSARY FUNDS THEREFOR.",
    "date_approved": "June 19, 1965",
    "source": "https://elibrary.judiciary.gov.ph/thebookshelf/showdocs/2/6867",
    "chunks": [
        {
            "chunk_index": 1,
            "text": "H. No. 7435 / 62 OG No. 38, 6818 (September 19, 1966)\n\n[ REPUBLIC ACT NO. 4424, June 19, 1965 ]\n\nAN ACT TO ESTABLISH A NATIONAL SCHOOL OF ARTS AND TRADES IN THE MUNICIPALITY OF CERVANTES, PROVINCE OF ILOCOS SUR, TO BE KNOWN AS CERVANTES NATIONAL SCHOOL OF ARTS AND TRADES, AND TO AUTHORIZE THE APPROPRIATION OF NECESSARY FUNDS THEREFOR.\n\nBe it enacted by the Senate and House of Representatives of the Philippines in Congress assembled:\n\nSECTION 1. There shall be established a national school of arts and trades in the Municipality of Cervantes, Province of Ilocos Sur, to be known as Cervantes National School of Arts and Trades.\n\nSEC. 2. The Secretary of Education shall issue such rules and regulations as may be necessary to carry out the purpose of this Act.\n\nSEC. 3. The sum of one hundred thousand pesos is hereby authorized to be appropriated, out of any funds in the National Treasury not otherwise appropriated, for the establishment, operation and maintenance of said school during the fiscal year nineteen hundred and sixty-six. Such sums as may be necessary in subsequent years shall be included in the annual General Appropriations Act.",
            "metadata": {
                "law_id": "RA_4424",
                "date": "June 19, 1965"
            }
        },
        {
            "chunk_index": 2,
            "text": "SEC. 4. This Act shall take effect upon its approval.\n\nApproved, June 19, 1965.",
            "metadata": {
                "law_id": "RA_4424",
                "date": "June 19, 1965"
            }
        }
    ]
}