{
    "document_id": "RA_4289",
    "title": "AN ACT CHANGING THE NAME OF THE MUNICIPAL DISTRICT OF CARABAO ISLAND IN THE PROVINCE OF ROMBLON TO MUNICIPAL DISTRICT OF SAN JOSE.",
    "date_approved": "June 19, 1965",
    "source": "https://elibrary.judiciary.gov.ph/thebookshelf/showdocs/2/6725",
    "chunks": [
        {
            "chunk_index": 1,
            "text": "H. No. 8588 / 62 OG No. 25, 4374 (June 20, 1966)\n\n[ REPUBLIC ACT NO. 4289, June 19, 1965 ]\n\nAN ACT CHANGING THE NAME OF THE MUNICIPAL DISTRICT OF CARABAO ISLAND IN THE PROVINCE OF ROMBLON TO MUNICIPAL DISTRICT OF SAN JOSE.\n\nBe it enacted by the Senate and House of Representatives of the Philippines in Congress assembled:\n\nSECTION 1. The Municipal District of Carabao Island in the Province of Roniblon shall hereafter be known for all intents and purposes as the Municipal District of San Jose.\n\nSEC. 2. This Act shall take effect upon its approval.\n\nApproved, June 19, 1965.",
            "metadata": {
                "law_id": "RA_4289",
                "date": "June 19, 1965"
            }
        }
    ]
}