{
    "document_id": "RA_4296",
    "title": "AN ACT PROVIDING FOR THE ESTABLISHMENT OF AN EMERGENCY HOSPITAL IN THE MUNICIPALITY OF TAFT, PROVINCE OF SAMAR, TO BE KNOWN AS TAFT EMERGENCY HOSPITAL, AND AUTHORIZING THE APPROPRIATION OF FUNDS THEREFOR.",
    "date_approved": "June 19, 1965",
    "source": "https://elibrary.judiciary.gov.ph/thebookshelf/showdocs/2/6732",
    "chunks": [
        {
            "chunk_index": 1,
            "text": "H. No. 8969 / 62 OG No. 25, 4377 (June 20, 1966)\n\n[ REPUBLIC ACT NO. 4296, June 19, 1965 ]\n\nAN ACT PROVIDING FOR THE ESTABLISHMENT OF AN EMERGENCY HOSPITAL IN THE MUNICIPALITY OF TAFT, PROVINCE OF SAMAR, TO BE KNOWN AS TAFT EMERGENCY HOSPITAL, AND AUTHORIZING THE APPROPRIATION OF FUNDS THEREFOR.\n\nBe it enacted by the Senate and House of Representatives of the Philippines in Congress assembled:\n\nSECTION 1. There is hereby established, under the supervision of the Department of Health, an emergency hospital in the Municipality of Taft, Province of Samar, to be known as Taft Emergency Hospital.\n\nSEC. 2. The Secretary of Health shall appoint such personnel as may be necessary to carry out the purpose of this Act.\n\nSEC. 3. Such sum as may be necessary to carry out the purpose of this Act is hereby authorized to be appropriated annually out of any funds in the National Treasury not otherwise appropriated.\n\nSEC. 4. This Act shall take effect upon its approval.\n\nApproved, June 19, 1965.",
            "metadata": {
                "law_id": "RA_4296",
                "date": "June 19, 1965"
            }
        }
    ]
}