{
    "document_id": "RA_4283",
    "title": "AN ACT CHANGING THE NAME OF WASHINGTON STREET IN ILIGAN CITY TO GENERAL EMILIO AGUINALDO STREET.",
    "date_approved": "June 19, 1965",
    "source": "https://elibrary.judiciary.gov.ph/thebookshelf/showdocs/2/6716",
    "chunks": [
        {
            "chunk_index": 1,
            "text": "H. No. 8347 / 62 OG No. 24, 4158 (June 13, 1966)\n\n[ REPUBLIC ACT NO. 4283, June 19, 1965 ]\n\nAN ACT CHANGING THE NAME OF WASHINGTON STREET IN ILIGAN CITY TO GENERAL EMILIO AGUINALDO STREET.\n\nBe it enacted by the Senate and House of Representatives of the Philippines in Congress assembled:\n\nSECTION 1. Washington Street in Iligan City shall hereafter be known and referred to as General Emilio Aguinaldo Street.\n\nSEC. 2. This Act shall take effect upon its approval.\n\nApproved, June 19, 1965.",
            "metadata": {
                "law_id": "RA_4283",
                "date": "June 19, 1965"
            }
        }
    ]
}