{
    "document_id": "RA_441",
    "title": "AN ACT TO EXTEND THE PERIOD FOR FILING PETITIONS FOR THE RECONSTITUTION OF RECORDS OF PENDING JUDICIAL PROCEEDINGS DESTROYED DURING THE LAST WAR.",
    "date_approved": "June 07, 1950",
    "source": "https://elibrary.judiciary.gov.ph/thebookshelf/showdocs/2/11880",
    "chunks": [
        {
            "chunk_index": 1,
            "text": "H. No. 1013 / 46 OG No. 6, 2464 (June, 1950)\n\n[ REPUBLIC ACT NO. 441, June 07, 1950 ]\n\nAN ACT TO EXTEND THE PERIOD FOR FILING PETITIONS FOR THE RECONSTITUTION OF RECORDS OF PENDING JUDICIAL PROCEEDINGS DESTROYED DURING THE LAST WAR.\n\nBe it enacted by the Senate and House of Representatives of the Philippines in Congress assembled:\n\nSECTION. 1. Notwithstanding the provisions of Act Numbered Three thousand one hundred and ten, the party or parties interested in any case pending in the courts the records of which have been destroyed by reason of the last Pacific war may file a petition for the reconstitution of such records within one year from the date of the approval of this Act.\n\nSEC. 2. The procedure, requirements and all other incidents of such reconstitution shall be governed by the provisions of Act Numbered Three thousand one hundred ten.\n\nSEC. 3. This Act shall take effect upon its approval.\n\nApproved, June 7, 1950.",
            "metadata": {
                "law_id": "RA_441",
                "date": "June 07, 1950"
            }
        }
    ]
}