{
    "document_id": "RA_5200",
    "title": "AN ACT CHANGING THE NAME OF LIPAY ELEÂ­MENTARY SCHOOL IN THE MUNICIPALITY OF SOLSONA, PROVINCE OF ILOCOS NORTE, TO NALIPSAN ELEMENTARY SCHOOL.",
    "date_approved": "April 27, 1968",
    "source": "https://elibrary.judiciary.gov.ph/thebookshelf/showdocs/2/24418",
    "chunks": [
        {
            "chunk_index": 1,
            "text": "H. No. 12481 / 65 OG No. 17, 4214 (April 28, 1969)\n\n[ REPUBLIC ACT NO. 5200, April 27, 1968 ]\n\nAN ACT CHANGING THE NAME OF LIPAY ELEÂMENTARY SCHOOL IN THE MUNICIPALITY OF SOLSONA, PROVINCE OF ILOCOS NORTE, TO NALIPSAN ELEMENTARY SCHOOL.\n\nBe it enacted by the Semite and House of Representatives of the Philippines in Congress assembled:\n\nSECTION 1. The name of the Lipay Elementary School in the Municipality of Solsona, Province of Ilocos Norte, is hereby change to Nalipsan Elementary School.\n\nSEC. 2. This Act shall take effect upon its approval.\n\nApproved, April 27, 1968.",
            "metadata": {
                "law_id": "RA_5200",
                "date": "April 27, 1968"
            }
        }
    ]
}