{
    "document_id": "RA_5607",
    "title": "AN ACT CHANGING THE NAME OF TALON ELEMENTARY SCHOOL IN ROXAS CITY TO ANTONIO VITERBO, SR. MEMORIAL SCHOOL.",
    "date_approved": "June 21, 1969",
    "source": "https://elibrary.judiciary.gov.ph/thebookshelf/showdocs/2/7494",
    "chunks": [
        {
            "chunk_index": 1,
            "text": "H. No. 14028 / 65 OG No. 48, 13278 (December 1, 1969)\n\n[ REPUBLIC ACT NO. 5607, June 21, 1969 ]\n\nAN ACT CHANGING THE NAME OF TALON ELEMENTARY SCHOOL IN ROXAS CITY TO ANTONIO VITERBO, SR. MEMORIAL SCHOOL.\n\nBe it enacted by the Senate and House of Representatives of the Philippines in Congress assembled:\n\nSECTION 1. The name of Talon Elementary School in Roxas City is hereby changed to Antonio Viterbo, Sr. Memorial School.\n\nSEC. 2. This Act shall take effect upon its approval.\n\nApproved, June 21, 1969.",
            "metadata": {
                "law_id": "RA_5607",
                "date": "June 21, 1969"
            }
        }
    ]
}