{
    "document_id": "RA_5707",
    "title": "AN ACT CONVERTING THE BUCAY RURAL HIGH SCHOOL IN THE MUNICIPALITY OF BUCAY, PROVINCE OF ABRA, TO A NATIONAL GENERAL HIGH SCHOOL, TO BE KNOWN AS THE BUCAY NATIONAL GENERAL HIGH SCHOOL.",
    "date_approved": "June 21, 1969",
    "source": "https://elibrary.judiciary.gov.ph/thebookshelf/showdocs/2/7675",
    "chunks": [
        {
            "chunk_index": 1,
            "text": "H. No. 18063 / 65 OG No. 52, 14380 (December 29, 1969)\n\n[ REPUBLIC ACT NO. 5707, June 21, 1969 ]\n\nAN ACT CONVERTING THE BUCAY RURAL HIGH SCHOOL IN THE MUNICIPALITY OF BUCAY, PROVINCE OF ABRA, TO A NATIONAL GENERAL HIGH SCHOOL, TO BE KNOWN AS THE BUCAY NATIONAL GENERAL HIGH SCHOOL.\n\nBe it enacted by the Senate and House of Representatives of the Philippines in Congress assembled:\n\nSECTION 1. The Bucay Rural High School in the Municipality of Bucay, Province of Abra, is hereby converted to a national general high school, to be known as the Bucay National General High School effective upon availability of funds.\n\nSEC. 2. All personnel, equipment, records, supplies appropriations and other assets, as well as liabilities, of the Bucay Rural High School are hereby transferred to the Bucay National General High School.\n\nSEC. 3. This Act shall take effect upon its approval.\n\nApproved, June 21, 1969.",
            "metadata": {
                "law_id": "RA_5707",
                "date": "June 21, 1969"
            }
        }
    ]
}