{
    "document_id": "RA_5715",
    "title": "AN ACT AMENDING SECTION THIRTY-FOUR OF REPUBLIC ACT NUMBERED FOUR THOUSAND ONE HUNDRED THIRTY-SIX.",
    "date_approved": "June 21, 1969",
    "source": "https://elibrary.judiciary.gov.ph/thebookshelf/showdocs/2/7685",
    "chunks": [
        {
            "chunk_index": 1,
            "text": "S. No. 944 / 65 OG No. 52, 14388 (December 29, 1969)\n\n[ REPUBLIC ACT NO. 5715, June 21, 1969 ]\n\nAN ACT AMENDING SECTION THIRTY-FOUR OF REPUBLIC ACT NUMBERED FOUR THOUSAND ONE HUNDRED THIRTY-SIX.\n\nBe it enacted by the Senate and House of Representatives of the Philippines in Congress assembled:\n\nSECTION 1. Subsection (g) of section thirty-four of Republic Act Numbered four thousand one hundred thirty-six is hereby amended to read as follows:\n\n\"(g)\n\nLights and reflector when parked or disabled\n\n.â Appropriate parking lights or flares visible one hundred meters away shall be displayed at a corner of the vehicle whenever such vehicle is parked on highways or in places that are not well-lighted or is placed in such manner as to endanger passing traffic. Furthermore, every motor vehicle shall be provided at all times with built-in reflectors or other similar warning devices either pasted, painted or attached at its front and back which shall likewise be visible at night at least one hundred meters away. No vehicle not provided with any of the requirements menÂtioned in this subsection shall be registered.\"",
            "metadata": {
                "law_id": "RA_5715",
                "date": "June 21, 1969"
            }
        },
        {
            "chunk_index": 2,
            "text": "SEC. 2. This Act shall take effect upon its approval.\n\nEnacted into law without executive signature on June 21, 1969.",
            "metadata": {
                "law_id": "RA_5715",
                "date": "June 21, 1969"
            }
        }
    ]
}