{
    "document_id": "RA_6438",
    "title": "AN ACT CHANGING THE NAME OF OCCIDENTAL NEGROS PROVINCIAL HOSPITAL IN THE CITY OF BACOLOD TO CORAZON LOCSIN-MONTELIBANO MEMORIAL HOSPITAL.",
    "date_approved": "June 17, 1972",
    "source": "https://elibrary.judiciary.gov.ph/thebookshelf/showdocs/2/1250",
    "chunks": [
        {
            "chunk_index": 1,
            "text": "H.No. 3428 / 68 OG No. 41, 8000-I (October 9, 1972)\n\n[ REPUBLIC ACT NO. 6438, June 17, 1972 ]\n\nAN ACT CHANGING THE NAME OF OCCIDENTAL NEGROS PROVINCIAL HOSPITAL IN THE CITY OF BACOLOD TO CORAZON LOCSIN-MONTELIBANO MEMORIAL HOSPITAL.\n\nBe it enacted by the Senate and House of Representatives of the Philippines in Congress assembled:\n\nSECTION 1. The name of Occidental Negros Provincial Hospital, situated in the City of Bacolod Philippines, is hereby changed and, henceforth, shall be named Corazon Locsin-Montelibano Memorial Hospital.\n\nSEC. 2. This Act shall take effect upon its approval.\n\nApproved, June 17, 1972.",
            "metadata": {
                "law_id": "RA_6438",
                "date": "June 17, 1972"
            }
        }
    ]
}