{
    "document_id": "RA_6486",
    "title": "AN ACT ESTABLISHING A SOIL CONSERVATION DEMONSTRATION STATION IN THE CITY OF PUERTO PRINCESA, AND AUTHORIZING THE APPROPRIATION OF FUNDS THEREFOR.",
    "date_approved": "June 17, 1972",
    "source": "https://elibrary.judiciary.gov.ph/thebookshelf/showdocs/2/965",
    "chunks": [
        {
            "chunk_index": 1,
            "text": "H. No. 966 / 68 OG No. 44, 8485 (October 30, 1972)\n\n[ REPUBLIC ACT NO. 6486, June 17, 1972 ]\n\nAN ACT ESTABLISHING A SOIL CONSERVATION DEMONSTRATION STATION IN THE CITY OF PUERTO PRINCESA, AND AUTHORIZING THE APPROPRIATION OF FUNDS THEREFOR.\n\nBe it enacted by the Senate and House of Representative; of the Philippines in Congress assembled:\n\nSECTION 1. There is hereby established a soil conservation demonstration station in the City of Puerto Princesa to be known as Puerto Princesa Soil Conservation Demonstration Station. The said station shall be under the direct supervision of the Director of Soils, and shall be subject to the provisions of Republic Act Numbered Six hundred twenty-two.\n\nSEC. 2. The sum of one hundred fifty thousand pesos is hereby authorized to be appropriated, out of any fund in the National Treasury not otherwise appropriated, for the establishment, operation and maintenance of said soil conservation demonstration station for the fiscal year nineteen hundred seventy-three. Thereafter, such sum as may be necessary for its operation and maintenance shall be included in the annual General Appropriations Act.",
            "metadata": {
                "law_id": "RA_6486",
                "date": "June 17, 1972"
            }
        },
        {
            "chunk_index": 2,
            "text": "SEC. 3. This Act shall take effect upon its approval. Enacted without the Executive approval, June 17, 1972.",
            "metadata": {
                "law_id": "RA_6486",
                "date": "June 17, 1972"
            }
        }
    ]
}