{
    "document_id": "RA_7786",
    "title": "AN ACT NAMING THE NATIONAL HIGHWAY BEGINNING FROM BARANGAY ANAYAN, MUNICIPALITY OF PILI UP TO THE MUNICIPALITY OF LAGONOY, PROVINCE OF CAMARINES SUR, AS THE GOVERNOR JOSE T. FUENTEBELLA NATIONAL HIGHWAY",
    "date_approved": "August 08, 1994",
    "source": "https://elibrary.judiciary.gov.ph/thebookshelf/showdocs/2/2465",
    "chunks": [
        {
            "chunk_index": 1,
            "text": "H. No. 9174 / 90 OG No. 40, 5928 (Oct. 3, 1994)\n\n[ REPUBLIC ACT NO. 7786, August 08, 1994 ]\n\nAN ACT NAMING THE NATIONAL HIGHWAY BEGINNING FROM BARANGAY ANAYAN, MUNICIPALITY OF PILI UP TO THE MUNICIPALITY OF LAGONOY, PROVINCE OF CAMARINES SUR, AS THE GOVERNOR JOSE T. FUENTEBELLA NATIONAL HIGHWAY\n\nBe it enacted by the Senate and House of Representatives of the Philippines in Congress assembled:\n\nSECTION 1. The national highway beginning from Barangay Anayan in the Municipality of Pili up to the Municipality of Lagonoy, Province of Camarines Sur, shall be named as the Governor Jose T. Fuentebella National Highway.\n\nSEC. 2. This Act shall take effect upon its approval.\n\nLapsed into law on August 8, 1994 without the President's signature, pursuant to Sec. 27(1), Article VI of the Constitution.",
            "metadata": {
                "law_id": "RA_7786",
                "date": "August 08, 1994"
            }
        }
    ]
}