{
    "document_id": "RA_9193",
    "title": "AN ACT DECLARING MARCH 7 OF EVERY YEAR A SPECIAL WORKING HOLIDAY IN THE CITY OF TAGUM, PROVINCE OF DAVAO DEL NORTE",
    "date_approved": "March 06, 2003",
    "source": "https://elibrary.judiciary.gov.ph/thebookshelf/showdocs/2/329",
    "chunks": [
        {
            "chunk_index": 1,
            "text": "H. No. 3542 / 99 OG No. 21, 3328 (May 26, 2003)\n\n[ REPUBLIC ACT NO. 9193, March 06, 2003 ]\n\nAN ACT DECLARING MARCH 7 OF EVERY YEAR A SPECIAL WORKING HOLIDAY IN THE CITY OF TAGUM, PROVINCE OF DAVAO DEL NORTE\n\nBe it enacted by the Senate and House of Representatives of the Philippines in Congress assembled:\n\nSECTION 1. It is hereby declared that March 7 of every year be a special working public holiday in the City of Tagum to enable its residents to fittingly commemorate and celebrate its foundation day.\n\nSEC. 2. This Act shall take effect upon its approval.\n\nApproved,\n\n(Sgd.) FRANKLIN M. DRILON\n\n(Sgd.) JOSE DE VENECIA JR.\n\nPresident of the Senate\n\nSpeaker of the House of Representatives\n\nThis Act which originated in the House of Representatives was finally passed by the House of Representatives and the Senate on March 6, 2002 and January 22, 2003, respectively.\n\n(Sgd.) OSCAR G. YABES\n\n(Sgd.) ROBERTO P. NAZARENO\n\nSecretary of the Senate\n\nSecretary General\n\nHouse of Representatives\n\nApproved: MAR 06 2003\n\n(Sgd.) GLORIA MACAPAGAL - ARROYO\n\nPresident of the Philippines",
            "metadata": {
                "law_id": "RA_9193",
                "date": "March 06, 2003"
            }
        }
    ]
}